audio_curation/__init__.py
audio_curation/archive_utility.py
audio_curation/audio_repo.py
audio_curation/tts.py
audio_curation/yt_music.py
audio_curation/episode_data/__init__.py
audio_curation/episode_data/google_sheets_data.py
audio_curation/scraping/__init__.py
audio_curation/scraping/cooltoad.py
audio_curation/scraping/youtube.py
audio_curation/segmentation/__init__.py
audio_curation/segmentation/amplitude_based.py
audio_curation/transcribe/__init__.py
audio_curation/transcribe/vosk_with_ffmpeg.py
audio_curation_projects/__init__.py
audio_curation_projects/archive_yt_misc.py
audio_curation_projects/general_tasks/__init__.py
audio_curation_projects/general_tasks/transcribe.py
audio_curation_projects/general_tasks/tts.py
audio_curation_projects/gmusic/__init__.py
audio_curation_projects/gmusic/__main__.py
audio_curation_projects/kaavya_audio/__init__.py
audio_curation_projects/kaavya_audio/durgA-saptashatI.py
audio_curation_projects/kaavya_audio/kathaasaritsaagara.py
audio_curation_projects/kaavya_audio/kirAtArjunIyam.py
audio_curation_projects/kaavya_audio/kumArasambhavam.py
audio_curation_projects/kaavya_audio/meghadUta.py
audio_curation_projects/kaavya_audio/raamacharitamaanasa.py
audio_curation_projects/kaavya_audio/raghuvamsha.py
audio_curation_projects/kaavya_audio/tiruppaavai.py
audio_curation_projects/kaavya_audio/tiruppaavai_pravachanam.py
audio_curation_projects/kannada_audio/__init__.py
audio_curation_projects/kannada_audio/__main__.py
audio_curation_projects/kannada_audio/archive_yt.py
audio_curation_projects/kannada_audio/kumaara_vyaasa.py
audio_curation_projects/kannada_audio/dvg_jnaapaka/__init__.py
audio_curation_projects/kannada_audio/dvg_jnaapaka/__main__.py
audio_curation_projects/mbh_audio/__init__.py
audio_curation_projects/mbh_audio/__main__.py
audio_curation_projects/mbh_audio/mbh_book.py
audio_curation_projects/rAmAyaNa_audio/__init__.py
audio_curation_projects/rAmAyaNa_audio/__main__.py
audio_curation-0.0.4.dist-info/LICENSE.txt
audio_curation-0.0.4.dist-info/METADATA
audio_curation-0.0.4.dist-info/WHEEL
audio_curation-0.0.4.dist-info/top_level.txt
audio_curation-0.0.4.dist-info/RECORD
