Metadata-Version: 2.1
Name: audio-curation
Version: 0.0.4
Summary: Some scripts for checking and curating audio file contributions to the Mahabharata audio project.
Home-page: https://github.com/sanskrit-coders/audio_curation
Author: Sanskrit programmers
Author-email: sanskrit-programmers@googlegroups.com
License: MIT
Keywords: audio internet-archive
Platform: UNKNOWN
Classifier: Development Status :: 5 - Production/Stable
Classifier: Intended Audience :: Education
Classifier: Topic :: Text Processing :: Linguistic
Classifier: License :: OSI Approved :: MIT License
Classifier: Programming Language :: Python :: 3
License-File: LICENSE.txt
Requires-Dist: pandas
Requires-Dist: internetarchive
Requires-Dist: ytmusicapi
Requires-Dist: audio-utils
Requires-Dist: curation-utils
Requires-Dist: GitPython
Requires-Dist: oauth2client
Requires-Dist: indic-transliteration
Requires-Dist: vosk
Requires-Dist: sanskrit-tts
Requires-Dist: yt-dlp
Provides-Extra: test
Requires-Dist: pytest ; extra == 'test'
